atyp/__init__.py
atyp/_modidx.py
atyp/_tmp.py
atyp/biol.py
atyp/bool.py
atyp/byte.py
atyp/clsv.py
atyp/cstm.py
atyp/enum.py
atyp/imgs.py
atyp/imps.py
atyp/insp.py
atyp/inst.py
atyp/iter.py
atyp/list.py
atyp/logr.py
atyp/npty.py
atyp/nums.py
atyp/path.py
atyp/pdty.py
atyp/plot.py
atyp/rich.py
atyp/sets.py
atyp/slcs.py
atyp/spty.py
atyp/strs.py
atyp/tens.py
atyp/tgrd.py
atyp/tqdm.py
atyp/type.py
atyp/typq.py
atyp/typr.py
atyp/typs.py
atyp-0.0.62.dist-info/LICENSE
atyp-0.0.62.dist-info/METADATA
atyp-0.0.62.dist-info/WHEEL
atyp-0.0.62.dist-info/entry_points.txt
atyp-0.0.62.dist-info/top_level.txt
atyp-0.0.62.dist-info/RECORD
